lektor_markdown_highlighter.py
lektor_markdown_highlighter-0.3.2.dist-info/LICENSE
lektor_markdown_highlighter-0.3.2.dist-info/METADATA
lektor_markdown_highlighter-0.3.2.dist-info/WHEEL
lektor_markdown_highlighter-0.3.2.dist-info/entry_points.txt
lektor_markdown_highlighter-0.3.2.dist-info/top_level.txt
lektor_markdown_highlighter-0.3.2.dist-info/RECORD
