Metadata-Version: 2.1
Name: lektor-markdown-highlighter
Version: 0.3.2
Summary: Lektor plugin that adds syntax highlighting for markdown blocks with Pygments.
Home-page: http://github.com/lektor/lektor-markdown-highlighter
Author: Armin Ronacher
Author-email: armin.ronacher@active-4.com
License: BSD
Keywords: Lektor plugin markdown static-site blog syntax-highlighter Pygments
Platform: UNKNOWN
Classifier: Environment :: Plugins
Classifier: Environment :: Web Environment
Classifier: Framework :: Lektor
Classifier: Intended Audience :: Developers
Classifier: License :: OSI Approved :: BSD License
License-File: LICENSE
Requires-Dist: Pygments
